telemetrix_uno_r4/__init__.py
telemetrix_uno_r4/minima/__init__.py
telemetrix_uno_r4/minima/telemetrix_uno_r4_minima/__init__.py
telemetrix_uno_r4/minima/telemetrix_uno_r4_minima/private_constants.py
telemetrix_uno_r4/minima/telemetrix_uno_r4_minima/telemetrix_uno_r4_minima.py
telemetrix_uno_r4/minima/telemetrix_uno_r4_minima_aio/__init__.py
telemetrix_uno_r4/minima/telemetrix_uno_r4_minima_aio/private_constants.py
telemetrix_uno_r4/minima/telemetrix_uno_r4_minima_aio/telemetrix_aio_serial.py
telemetrix_uno_r4/minima/telemetrix_uno_r4_minima_aio/telemetrix_uno_r4_minima_aio.py
telemetrix_uno_r4/r4_minima_examples/asyncio/msa_analog_input.py
telemetrix_uno_r4/r4_minima_examples/asyncio/msa_blink.py
telemetrix_uno_r4/r4_minima_examples/asyncio/msa_dht.py
telemetrix_uno_r4/r4_minima_examples/asyncio/msa_digital_input.py
telemetrix_uno_r4/r4_minima_examples/asyncio/msa_digital_input_pullup.py
telemetrix_uno_r4/r4_minima_examples/asyncio/msa_fade.py
telemetrix_uno_r4/r4_minima_examples/asyncio/msa_hc-sr04_distance_sensor.py
telemetrix_uno_r4/r4_minima_examples/asyncio/msa_i2c_adxl345_accelerometer.py
telemetrix_uno_r4/r4_minima_examples/asyncio/msa_loop_back.py
telemetrix_uno_r4/r4_minima_examples/asyncio/msa_servo.py
telemetrix_uno_r4/r4_minima_examples/asyncio/msa_sonar_disable.py
telemetrix_uno_r4/r4_minima_examples/asyncio/msa_spi_adxl345_accelerometer.py
telemetrix_uno_r4/r4_minima_examples/threaded/mst_analog_input.py
telemetrix_uno_r4/r4_minima_examples/threaded/mst_blink.py
telemetrix_uno_r4/r4_minima_examples/threaded/mst_dht.py
telemetrix_uno_r4/r4_minima_examples/threaded/mst_digital_input.py
telemetrix_uno_r4/r4_minima_examples/threaded/mst_digital_input_pullup.py
telemetrix_uno_r4/r4_minima_examples/threaded/mst_fade.py
telemetrix_uno_r4/r4_minima_examples/threaded/mst_hc-sr04_distance_sensor.py
telemetrix_uno_r4/r4_minima_examples/threaded/mst_i2c_adxl345_accelerometer.py
telemetrix_uno_r4/r4_minima_examples/threaded/mst_loop_back.py
telemetrix_uno_r4-1.1.1.dist-info/METADATA
telemetrix_uno_r4-1.1.1.dist-info/WHEEL
telemetrix_uno_r4-1.1.1.dist-info/top_level.txt
telemetrix_uno_r4-1.1.1.dist-info/RECORD
