Metadata-Version: 2.1
Name: telemetrix_uno_r4
Version: 1.1.1
Summary: Telemetrix Clients Supporting The Arduino Uno R4 Minima and Wifi
Author-email: Alan Yorinks <MisterYsLab@gmail.com>
License: AGPL-3.0-or-later
Keywords: telemetrix,Arduino,R4,Python
Classifier: Development Status :: 5 - Production/Stable
Classifier: Environment :: Other Environment
Classifier: Intended Audience :: Developers
Classifier: Intended Audience :: Education
Classifier: Operating System :: OS Independent
Classifier: Topic :: Software Development :: Libraries :: Python Modules
Requires-Python: >=3.8
Requires-Dist: pyserial
Requires-Dist: bleak
